{
  "name": "feffery_utils_components",
  "version": "0.1.4",
  "description": "Build more utility components for Plotly Dash.",
  "repository": {
    "type": "git",
    "url": "git://github.com/https://github.com/CNFeffery/feffery-utils-components.git"
  },
  "bugs": {
    "url": "https://github.com/https://github.com/CNFeffery/feffery-utils-components/issues"
  },
  "homepage": "https://github.com/https://github.com/CNFeffery/feffery-utils-components",
  "main": "build/index.js",
  "scripts": {
    "start": "webpack-serve --config ./webpack.serve.config.js --open",
    "build:js": "webpack --mode production",
    "build:backends": "dash-generate-components ./src/lib/components feffery_utils_components -p package-info.json --r-prefix '' --jl-prefix ''",
    "build:backends-activated": "(. venv/bin/activate || venv\\scripts\\activate && npm run build:py_and_r)",
    "build": "npm run build:js && npm run build:backends",
    "build:activated": "npm run build:js && npm run build:backends-activated"
  },
  "author": "CNFeffery <fefferypzy@gmail.com>",
  "license": "MIT",
  "dependencies": {
    "@ant-design/icons": "^4.7.0",
    "@uiw/color-convert": "^1.1.0",
    "@uiw/react-color-wheel": "^1.1.0",
    "ahooks": "^3.7.0",
    "array-move": "^4.0.0",
    "byte-guide": "^1.0.7",
    "interweave": "^13.0.0",
    "lodash": "^4.17.21",
    "ninja-keys": "^1.1.12",
    "nprogress": "^0.2.0",
    "qrcode.react": "^3.1.0",
    "ramda": "^0.26.1",
    "rc-virtual-list": "^3.4.8",
    "react-captcha-code": "^1.0.7",
    "react-color": "^2.19.3",
    "react-colorful": "^5.6.1",
    "react-copy-to-clipboard": "^5.0.4",
    "react-highlight-words": "^0.18.0",
    "react-hot-toast": "^2.4.0",
    "react-lazy-load": "^3.1.14",
    "react-lazy-load-image-component": "^1.5.5",
    "react-resize-detector": "^7.1.2",
    "react-scroll": "^1.8.6",
    "react-sortable-hoc": "^2.0.0",
    "react-spinners-kit": "^1.9.1",
    "react-split": "^2.0.14",
    "react-stickynode": "^4.1.0",
    "react-syntax-highlighter": "^15.4.4",
    "react-toastify": "9.0.3",
    "react-use": "^17.4.0",
    "simplebar-react": "^2.3.7",
    "use-eye-dropper": "^1.4.3"
  },
  "devDependencies": {
    "@babel/core": "^7.5.4",
    "@babel/plugin-proposal-object-rest-spread": "^7.5.4",
    "@babel/plugin-proposal-optional-chaining": "^7.18.9",
    "@babel/preset-env": "^7.5.4",
    "@babel/preset-react": "^7.0.0",
    "@plotly/dash-component-plugins": "^1.2.3",
    "@plotly/webpack-dash-dynamic-import": "^1.2.0",
    "babel-eslint": "^10.0.2",
    "babel-loader": "^8.0.6",
    "copyfiles": "^2.1.1",
    "css-loader": "^3.0.0",
    "eslint": "^6.0.1",
    "eslint-config-prettier": "^6.0.0",
    "eslint-plugin-import": "^2.18.0",
    "eslint-plugin-react": "^7.14.2",
    "file-loader": "^6.2.0",
    "less": "^3.13.1",
    "less-loader": "^5.0.0",
    "npm": "^6.1.0",
    "prop-types": "^15.7.2",
    "react": "^16.8.6",
    "react-docgen": "^4.1.1",
    "react-dom": "^16.8.6",
    "style-loader": "^0.23.1",
    "styled-jsx": "^3.4.7",
    "terser-webpack-plugin": "^2.3.0",
    "url-loader": "^4.1.1",
    "webpack": "4.36.1",
    "webpack-cli": "3.3.6",
    "webpack-serve": "3.1.0"
  },
  "babel": {
    "presets": [
      "@babel/preset-react",
      "@babel/preset-env"
    ],
    "plugins": [
      "@babel/plugin-transform-react-jsx",
      "styled-jsx/babel"
    ]
  },
  "engines": {
    "node": ">=8.11.0",
    "npm": ">=6.1.0"
  }
}
